<?xml version='1.0' encoding='UTF-8'?>
<faces-config version="2.2"
              xmlns="http://xmlns.jcp.org/xml/ns/javaee"
              xmlns:xsi="http://www.w3.org/2001/XMLSchema-instance"
              xsi:schemaLocation="http://xmlns.jcp.org/xml/ns/javaee http://xmlns.jcp.org/xml/ns/javaee/web-facesconfig_2_2.xsd">
    <navigation-rule>
        <from-view-id>/index.xhtml</from-view-id>
        <navigation-case>
            <from-outcome>index</from-outcome>
            <to-view-id>/index.xhtml</to-view-id>
        </navigation-case>
        <navigation-case>
            <from-outcome>login</from-outcome>
            <to-view-id>/login.xhtml</to-view-id>
        </navigation-case>
        <navigation-case>
            <from-outcome>registroalumno</from-outcome>
            <to-view-id>/registraAlumno.xhtml</to-view-id>
        </navigation-case>
        <navigation-case>
            <from-outcome>registroprofesor</from-outcome>
            <to-view-id>/registraProfesor.xhtml</to-view-id>
        </navigation-case>
        <navigation-case>
            <from-outcome>inicioalumno</from-outcome>
            <to-view-id>/inicioAlumno.xhtml</to-view-id>
        </navigation-case>
        <navigation-case>
            <from-outcome>inicioprofesor</from-outcome>
            <to-view-id>/inicioProfesor.xhtml</to-view-id>
        </navigation-case>
        <navigation-case>
            <from-outcome>modificarperfil</from-outcome>
            <to-view-id>/modificarProfesor.xhtml</to-view-id>
        </navigation-case>
        <navigation-case>
            <from-outcome>nuevapublicacion</from-outcome>
            <to-view-id>/nuevaPublicacion.xhtml</to-view-id>
        </navigation-case>
    </navigation-rule>
    <navigation-rule>
        <from-view-id>/login.xhtml</from-view-id>
        <navigation-case>
            <from-outcome>index</from-outcome>
            <to-view-id>/index.xhtml</to-view-id>
        </navigation-case>
        <navigation-case>
            <from-outcome>login</from-outcome>
            <to-view-id>/login.xhtml</to-view-id>
        </navigation-case>
        <navigation-case>
            <from-outcome>registroalumno</from-outcome>
            <to-view-id>/registraAlumno.xhtml</to-view-id>
        </navigation-case>
        <navigation-case>
            <from-outcome>registroprofesor</from-outcome>
            <to-view-id>/registraProfesor.xhtml</to-view-id>
        </navigation-case>
        <navigation-case>
            <from-outcome>inicioalumno</from-outcome>
            <to-view-id>/inicioAlumno.xhtml</to-view-id>
        </navigation-case>
        <navigation-case>
            <from-outcome>inicioprofesor</from-outcome>
            <to-view-id>/inicioProfesor.xhtml</to-view-id>
        </navigation-case>
        <navigation-case>
            <from-outcome>modificarperfil</from-outcome>
            <to-view-id>/modificarProfesor.xhtml</to-view-id>
        </navigation-case>
        <navigation-case>
            <from-outcome>nuevapublicacion</from-outcome>
            <to-view-id>/nuevaPublicacion.xhtml</to-view-id>
        </navigation-case>
    </navigation-rule>
    <navigation-rule>
        <from-view-id>/registraAlumno.xhtml</from-view-id>
        <navigation-case>
            <from-outcome>index</from-outcome>
            <to-view-id>/index.xhtml</to-view-id>
        </navigation-case>
        <navigation-case>
            <from-outcome>login</from-outcome>
            <to-view-id>/login.xhtml</to-view-id>
        </navigation-case>
        <navigation-case>
            <from-outcome>registroalumno</from-outcome>
            <to-view-id>/registraAlumno.xhtml</to-view-id>
        </navigation-case>
        <navigation-case>
            <from-outcome>registroprofesor</from-outcome>
            <to-view-id>/registraProfesor.xhtml</to-view-id>
        </navigation-case>
        <navigation-case>
            <from-outcome>inicioalumno</from-outcome>
            <to-view-id>/inicioAlumno.xhtml</to-view-id>
        </navigation-case>
        <navigation-case>
            <from-outcome>inicioprofesor</from-outcome>
            <to-view-id>/inicioProfesor.xhtml</to-view-id>
        </navigation-case>
        <navigation-case>
            <from-outcome>modificarperfil</from-outcome>
            <to-view-id>/modificarProfesor.xhtml</to-view-id>
        </navigation-case>
        <navigation-case>
            <from-outcome>nuevapublicacion</from-outcome>
            <to-view-id>/nuevaPublicacion.xhtml</to-view-id>
        </navigation-case>
    </navigation-rule>
    <navigation-rule>
        <from-view-id>/registraProfesor.xhtml</from-view-id>
        <navigation-case>
            <from-outcome>index</from-outcome>
            <to-view-id>/index.xhtml</to-view-id>
        </navigation-case>
        <navigation-case>
            <from-outcome>login</from-outcome>
            <to-view-id>/login.xhtml</to-view-id>
        </navigation-case>
        <navigation-case>
            <from-outcome>registroalumno</from-outcome>
            <to-view-id>/registraAlumno.xhtml</to-view-id>
        </navigation-case>
        <navigation-case>
            <from-outcome>registroprofesor</from-outcome>
            <to-view-id>/registraProfesor.xhtml</to-view-id>
        </navigation-case>
        <navigation-case>
            <from-outcome>inicioalumno</from-outcome>
            <to-view-id>/inicioAlumno.xhtml</to-view-id>
        </navigation-case>
        <navigation-case>
            <from-outcome>inicioprofesor</from-outcome>
            <to-view-id>/inicioProfesor.xhtml</to-view-id>
        </navigation-case>
        <navigation-case>
            <from-outcome>modificarperfil</from-outcome>
            <to-view-id>/modificarProfesor.xhtml</to-view-id>
        </navigation-case>
        <navigation-case>
            <from-outcome>nuevapublicacion</from-outcome>
            <to-view-id>/nuevaPublicacion.xhtml</to-view-id>
        </navigation-case>
    </navigation-rule>
    <navigation-rule>
        <from-view-id>/inicioAlumno.xhtml</from-view-id>
        <navigation-case>
            <from-outcome>index</from-outcome>
            <to-view-id>/index.xhtml</to-view-id>
        </navigation-case>
        <navigation-case>
            <from-outcome>login</from-outcome>
            <to-view-id>/login.xhtml</to-view-id>
        </navigation-case>
        <navigation-case>
            <from-outcome>registroalumno</from-outcome>
            <to-view-id>/registraAlumno.xhtml</to-view-id>
        </navigation-case>
        <navigation-case>
            <from-outcome>registroprofesor</from-outcome>
            <to-view-id>/registraProfesor.xhtml</to-view-id>
        </navigation-case>
        <navigation-case>
            <from-outcome>inicioalumno</from-outcome>
            <to-view-id>/inicioAlumno.xhtml</to-view-id>
        </navigation-case>
        <navigation-case>
            <from-outcome>inicioprofesor</from-outcome>
            <to-view-id>/inicioProfesor.xhtml</to-view-id>
        </navigation-case>
        <navigation-case>
            <from-outcome>modificarperfil</from-outcome>
            <to-view-id>/modificarProfesor.xhtml</to-view-id>
        </navigation-case>
        <navigation-case>
            <from-outcome>nuevapublicacion</from-outcome>
            <to-view-id>/nuevaPublicacion.xhtml</to-view-id>
        </navigation-case>
        <navigation-case>
            <from-outcome>veractividades</from-outcome>
            <to-view-id>/verActividades.xhtml</to-view-id>
        </navigation-case>
    </navigation-rule>
    <navigation-rule>
        <from-view-id>/inicioProfesor.xhtml</from-view-id>
        <navigation-case>
            <from-outcome>index</from-outcome>
            <to-view-id>/index.xhtml</to-view-id>
        </navigation-case>
        <navigation-case>
            <from-outcome>login</from-outcome>
            <to-view-id>/login.xhtml</to-view-id>
        </navigation-case>
        <navigation-case>
            <from-outcome>registroalumno</from-outcome>
            <to-view-id>/registraAlumno.xhtml</to-view-id>
        </navigation-case>
        <navigation-case>
            <from-outcome>registroprofesor</from-outcome>
            <to-view-id>/registraProfesor.xhtml</to-view-id>
        </navigation-case>
        <navigation-case>
            <from-outcome>inicioalumno</from-outcome>
            <to-view-id>/inicioAlumno.xhtml</to-view-id>
        </navigation-case>
        <navigation-case>
            <from-outcome>inicioprofesor</from-outcome>
            <to-view-id>/inicioProfesor.xhtml</to-view-id>
        </navigation-case>
        <navigation-case>
            <from-outcome>modificarperfil</from-outcome>
            <to-view-id>/modificarProfesor.xhtml</to-view-id>
        </navigation-case>
        <navigation-case>
            <from-outcome>nuevapublicacion</from-outcome>
            <to-view-id>/nuevaPublicacion.xhtml</to-view-id>
        </navigation-case>
        <navigation-case>
            <from-outcome>misactividades</from-outcome>
            <to-view-id>/misActividades.xhtml</to-view-id>
        </navigation-case>
    </navigation-rule>
    <navigation-rule>
        <from-view-id>/modificarProfesor.xhtml</from-view-id>
        <navigation-case>
            <from-outcome>index</from-outcome>
            <to-view-id>/index.xhtml</to-view-id>
        </navigation-case>
        <navigation-case>
            <from-outcome>login</from-outcome>
            <to-view-id>/login.xhtml</to-view-id>
        </navigation-case>
        <navigation-case>
            <from-outcome>registroalumno</from-outcome>
            <to-view-id>/registraAlumno.xhtml</to-view-id>
        </navigation-case>
        <navigation-case>
            <from-outcome>registroprofesor</from-outcome>
            <to-view-id>/registraProfesor.xhtml</to-view-id>
        </navigation-case>
        <navigation-case>
            <from-outcome>inicioalumno</from-outcome>
            <to-view-id>/inicioAlumno.xhtml</to-view-id>
        </navigation-case>
        <navigation-case>
            <from-outcome>inicioprofesor</from-outcome>
            <to-view-id>/inicioProfesor.xhtml</to-view-id>
        </navigation-case>
        <navigation-case>
            <from-outcome>modificarperfil</from-outcome>
            <to-view-id>/modificarProfesor.xhtml</to-view-id>
        </navigation-case>
        <navigation-case>
            <from-outcome>nuevapublicacion</from-outcome>
            <to-view-id>/nuevaPublicacion.xhtml</to-view-id>
        </navigation-case>
    </navigation-rule>
    <navigation-rule>
        <from-view-id>/nuevaPublicacion.xhtml</from-view-id>
        <navigation-case>
            <from-outcome>index</from-outcome>
            <to-view-id>/index.xhtml</to-view-id>
        </navigation-case>
        <navigation-case>
            <from-outcome>login</from-outcome>
            <to-view-id>/login.xhtml</to-view-id>
        </navigation-case>
        <navigation-case>
            <from-outcome>registroalumno</from-outcome>
            <to-view-id>/registraAlumno.xhtml</to-view-id>
        </navigation-case>
        <navigation-case>
            <from-outcome>registroprofesor</from-outcome>
            <to-view-id>/registraProfesor.xhtml</to-view-id>
        </navigation-case>
        <navigation-case>
            <from-outcome>inicioalumno</from-outcome>
            <to-view-id>/inicioAlumno.xhtml</to-view-id>
        </navigation-case>
        <navigation-case>
            <from-outcome>inicioprofesor</from-outcome>
            <to-view-id>/inicioProfesor.xhtml</to-view-id>
        </navigation-case>
        <navigation-case>
            <from-outcome>modificarperfil</from-outcome>
            <to-view-id>/modificarProfesor.xhtml</to-view-id>
        </navigation-case>
        <navigation-case>
            <from-outcome>nuevapublicacion</from-outcome>
            <to-view-id>/nuevaPublicacion.xhtml</to-view-id>
        </navigation-case>
    </navigation-rule>
    <navigation-rule>
        <from-view-id>/misActividades.xhtml</from-view-id>
        <navigation-case>
            <from-outcome>inicioprofesor</from-outcome>
            <to-view-id>/inicioProfesor.xhtml</to-view-id>
        </navigation-case>
    </navigation-rule>
    <navigation-rule>
        <from-view-id>/verActividades.xhtml</from-view-id>
        <navigation-case>
            <from-outcome>inicioalumno</from-outcome>
            <to-view-id>/inicioAlumno.xhtml</to-view-id>
        </navigation-case>
    </navigation-rule>
</faces-config>